{
  "blogs": [
    {
      "id": 1782323418,
      "title": "🚀 The Ultimate Master Guide to SmartGen Tools: 40+ Free Utilities for Professionals",
      "excerpt": "*Written by Sayad Md Bayezid Hosan | Founder & Lead Consultant, Connect With Bayezid | A GenZ Frontier Initiative*",
      "category": "General",
      "date": "2026-06-24",
      "image": "https://i.postimg.cc/8zs6Nvj1/27029CEE-5CD8-43AE-85D0-51C18A4BF0C8-Original.png",
      "slug": "the-ultimate-master-guide-to-smartgen-tools-40-free-utilities-for-professionals"
    }
  ]
}